simple_list_editable/__init__.py
simple_list_editable/admin.py
django_simple_list_editable-1.0.1.dist-info/LICENSE
django_simple_list_editable-1.0.1.dist-info/METADATA
django_simple_list_editable-1.0.1.dist-info/WHEEL
django_simple_list_editable-1.0.1.dist-info/top_level.txt
django_simple_list_editable-1.0.1.dist-info/RECORD
