Metadata-Version: 2.1
Name: django-simple-list-editable
Version: 1.0.1
Summary: Provides a simple list_editable attribute control in Django Admin, based on http request and self context
Requires-Python: >=3.12
License-File: LICENSE
Requires-Dist: django >=5.1.1
